anvil/__init__.py
anvil/block.py
anvil/chunk.py
anvil/empty_chunk.py
anvil/empty_region.py
anvil/empty_section.py
anvil/errors.py
anvil/raw_section.py
anvil/region.py
anvil_new-1.0.1.dist-info/LICENSE
anvil_new-1.0.1.dist-info/METADATA
anvil_new-1.0.1.dist-info/WHEEL
anvil_new-1.0.1.dist-info/top_level.txt
anvil_new-1.0.1.dist-info/RECORD
