Metadata-Version: 2.1
Name: anvil-new
Version: 1.0.1
Summary: A Minecraft anvil file format parser, designed to work with minecraft versions 1.16+.
Home-page: https://github.com/intergalactyc/anvil-new
Author: intergalactyc
Classifier: Programming Language :: Python :: 3
Classifier: License :: OSI Approved :: MIT License
Classifier: Operating System :: OS Independent
License-File: LICENSE
Requires-Dist: nbt
Requires-Dist: frozendict
